xiaomi_mi_scale/Xiaomi_Scale_Body_Metrics.py
xiaomi_mi_scale/__init__.py
xiaomi_mi_scale/body_scales.py
xiaomi_mi_scale/body_score.py
xiaomi_mi_scale/parser.py
xiaomi_mi_scale-0.0.20.dist-info/METADATA
xiaomi_mi_scale-0.0.20.dist-info/WHEEL
xiaomi_mi_scale-0.0.20.dist-info/entry_points.txt
xiaomi_mi_scale-0.0.20.dist-info/license_files/LICENSE
xiaomi_mi_scale-0.0.20.dist-info/RECORD
